gammahill_distributions/Binomialdistribution.py
gammahill_distributions/Gaussiandistribution.py
gammahill_distributions/Generaldistribution.py
gammahill_distributions/__init__.py
gammahill_distributions-0.2.dist-info/METADATA
gammahill_distributions-0.2.dist-info/WHEEL
gammahill_distributions-0.2.dist-info/top_level.txt
gammahill_distributions-0.2.dist-info/RECORD
