Metadata-Version: 2.1
Name: gammahill-distributions
Version: 0.2
Summary: Gaussian distribution
Home-page: UNKNOWN
Author: Solomon Igori
Author-email: igorisolomon@gmail.com
License: UNKNOWN
Platform: UNKNOWN
